{
  "required": true,
  "package": "com.iridium126.createtricks.mixin",
  "plugin": "com.iridium126.createtricks.mixin.CreateTricksMixinPlugin",
  "compatibilityLevel": "JAVA_21",
  "mixins": [
    "FillingBySpoutMixin",
    "GenericItemFillingContextMixin",
    "GenericItemEmptyingContextMixin",
    "KineticBlockEntityAccessor",
    "KineticBlockEntityMixin",
    "KineticBlockEntitySyncMixin",
    "KineticBlockEntityVisualMixin",
    "DirectionalShaftHalvesBlockEntityMixin",
    "KineticsSpellCoreItemMixin",
    "ModelsMixin",
    "TricksterSpellConstructSyncMixin",
    "TrickBlunderExceptionMixin",
    "MechanicalPressKnotMixin",
    "bnb.CogwheelChainMixin",
    "bnb.CogwheelChainPathNodesMixin",
    "bnb.CogwheelChainPlaceInLevelMixin",
    "bnb.CogwheelChainBlockEntityStressMixin",
    "bnb.CogwheelChainPlacementInteractionMixin",
    "bnb.CogwheelChainCandidateMixin",
    "bnb.PlacingCogwheelChainMixin",
    "bnb.PlaceCogwheelChainPacketMixin"
  ],
  "client": [
    "CachedBuffersMixin",
    "LiquidBlockRendererMixin",
    "ModularSpellConstructBlockEntityRendererMixin",
    "SafeBlockEntityRendererMixin",
    "bnb.CogwheelChainBehaviourRendererMixin",
    "bnb.CogwheelChainBehaviourVisualMixin"
  ],
  "injectors": {
    "defaultRequire": 1
  },
  "overwrites": {
    "requireAnnotations": true
  }
}
